clone_org/__init__.py
clone_org/arg_parsing/__init__.py
clone_org/arg_parsing/parse_cmd_line.py
clone_org/clone/__init__.py
clone_org/clone/shell_clone.py
clone_org/main.py
clone_org/query_github/.graphqlconfig
clone_org/query_github/README.rst
clone_org/query_github/__init__.py
clone_org/query_github/fetch_org_repos.py
clone_org/query_github/github-schema.graphql
clone_org/query_github/org-repos-count.graphql
clone_org/query_github/org-repos.graphql
clone_org/utils/__init__.py
clone_org/utils/check_dict.py
clone_org-1.0.12.dist-info/METADATA
clone_org-1.0.12.dist-info/WHEEL
clone_org-1.0.12.dist-info/entry_points.txt
clone_org-1.0.12.dist-info/licenses/LICENSE.txt
clone_org-1.0.12.dist-info/RECORD
