Metadata-Version: 2.4
Name: clone-org
Version: 1.0.12
Summary: Clone all the repos or just some by language from an org
License: Apache-2.0
License-File: LICENSE.txt
Author: Glenn Hinks
Author-email: ghinks@yahoo.com
Requires-Python: >=3.8.1,<4.0.0
Classifier: License :: OSI Approved :: Apache Software License
Classifier: Programming Language :: Python :: 3
Classifier: Programming Language :: Python :: 3.9
Classifier: Programming Language :: Python :: 3.10
Classifier: Programming Language :: Python :: 3.11
Classifier: Programming Language :: Python :: 3.12
Classifier: Programming Language :: Python :: 3.13
Classifier: Programming Language :: Python :: 3.14
Requires-Dist: flake8 (>=6.1,<8.0)
Requires-Dist: pytest (>=7.4.3,<9.0.0)
Requires-Dist: sgqlc (>=16.3,<18.0)
Requires-Dist: tabulate (>=0.9.0,<0.10.0)
Project-URL: Homepage, https://github.com/ghinks/clone-org
Project-URL: Repository, https://github.com/ghinks/clone-org
